EAP/__init__.py
EAP/adjust.py
EAP/api.py
EAP/autoencoder.py
EAP/cross_section_regress.py
EAP/fama_macbeth.py
EAP/portfolio_analysis.py
EAP/time_frequency.py
EAP/time_series_regress.py
EAP/util.py
EAP/test/__init__.py
EAP/test/test_adjust.py
EAP/test/test_autoencoder.py
EAP/test/test_cross_section_regress.py
EAP/test/test_fama_macbeth.py
EAP/test/test_portfolio_analysis.py
EAP/test/test_time_frequency.py
EAP/test/test_time_series_regress.py
EAP/test/test_util.py
EAP-1.1.11.dist-info/LICENSE
EAP-1.1.11.dist-info/METADATA
EAP-1.1.11.dist-info/WHEEL
EAP-1.1.11.dist-info/top_level.txt
EAP-1.1.11.dist-info/RECORD
