Metadata-Version: 2.1
Name: EAP
Version: 1.1.11
Summary: This package is designed for empirical asset pricing
Home-page: https://whyecofiliter.github.io/EAP/
Author: whyecofiliter
Author-email: why_ecofiliter@126.com
License: MIT
Project-URL: Bug Tracker, https://github.com/whyecofiliter/EAP/issues
Project-URL: Documentation, https://whyecofiliter.github.io/EAP/Documentation.html
Project-URL: Source Code, https://github.com/whyecofiliter/EAP
Platform: UNKNOWN
Classifier: Programming Language :: Python :: 3
Classifier: License :: OSI Approved :: MIT License
Classifier: Operating System :: OS Independent
Requires-Python: >=3
Requires-Dist: numpy
Requires-Dist: pandas
Requires-Dist: matplotlib
Requires-Dist: scipy
Requires-Dist: statsmodels
Requires-Dist: prettytable
Requires-Dist: tensorflow
Requires-Dist: pywavelets
Requires-Dist: seaborn
